mlx_gui/__init__.py
mlx_gui/app_main.py
mlx_gui/audio_manager.py
mlx_gui/cli.py
mlx_gui/database.py
mlx_gui/download_progress.py
mlx_gui/huggingface_integration.py
mlx_gui/inference_queue_manager.py
mlx_gui/mlx_integration.py
mlx_gui/model_manager.py
mlx_gui/models.py
mlx_gui/queued_inference.py
mlx_gui/server.py
mlx_gui/system_monitor.py
mlx_gui/tray.py
mlx_gui/templates/admin.html
mlx_gui-1.3.0.dist-info/METADATA
mlx_gui-1.3.0.dist-info/WHEEL
mlx_gui-1.3.0.dist-info/entry_points.txt
mlx_gui-1.3.0.dist-info/licenses/LICENSE
mlx_gui-1.3.0.dist-info/RECORD
