Metadata-Version: 2.4
Name: mlx-gui
Version: 1.3.0
Summary: A lightweight RESTful wrapper around Apple's MLX engine for dynamically loading and serving MLX-compatible models
Project-URL: Homepage, https://github.com/ramborogers/mlx-gui
Project-URL: Repository, https://github.com/ramborogers/mlx-gui
Project-URL: Issues, https://github.com/ramborogers/mlx-gui/issues
Author-email: Matt Rogers <matt@matthewrogers.org>
License: GPL-3.0
License-File: LICENSE
Keywords: apple,gui,machine-learning,mlx,rest-api
Classifier: Development Status :: 3 - Alpha
Classifier: Intended Audience :: Developers
Classifier: License :: OSI Approved :: GNU General Public License v3 (GPLv3)
Classifier: Operating System :: MacOS
Classifier: Programming Language :: Python :: 3
Classifier: Programming Language :: Python :: 3.11
Classifier: Topic :: Scientific/Engineering :: Artificial Intelligence
Requires-Python: >=3.11
Requires-Dist: aiofiles>=23.2.0
Requires-Dist: appdirs>=1.4.4
Requires-Dist: click>=8.1.0
Requires-Dist: fastapi>=0.104.0
Requires-Dist: httpx>=0.25.0
Requires-Dist: huggingface-hub>=0.19.0
Requires-Dist: mlx-audio>=0.2.6
Requires-Dist: mlx-embedding-models>=0.0.11
Requires-Dist: mlx-embeddings>=0.0.5
Requires-Dist: mlx-lm>=0.28.4
Requires-Dist: mlx-vlm>=0.3.9
Requires-Dist: mlx-whisper>=0.4.3
Requires-Dist: parakeet-mlx>=0.4.1
Requires-Dist: psutil>=5.9.0
Requires-Dist: pydantic>=2.0.0
Requires-Dist: python-multipart>=0.0.6
Requires-Dist: rich>=13.6.0
Requires-Dist: rumps>=0.4.0
Requires-Dist: sqlalchemy>=2.0.0
Requires-Dist: timm>=1.0.19
Requires-Dist: torchvision>=0.22.1
Requires-Dist: typer>=0.9.0
Requires-Dist: uvicorn[standard]>=0.24.0
Provides-Extra: app
Requires-Dist: pillow>=10.0.0; extra == 'app'
Requires-Dist: pyinstaller>=6.0.0; extra == 'app'
Requires-Dist: rumps>=0.4.0; extra == 'app'
Requires-Dist: sentencepiece>=0.2.0; extra == 'app'
Requires-Dist: tokenizers>=0.21.0; extra == 'app'
Requires-Dist: transformers>=4.57.3; extra == 'app'
Provides-Extra: audio
Requires-Dist: mlx-audio>=0.2.6; extra == 'audio'
Requires-Dist: mlx-whisper>=0.4.3; extra == 'audio'
Provides-Extra: dev
Requires-Dist: black>=23.9.0; extra == 'dev'
Requires-Dist: mypy>=1.6.0; extra == 'dev'
Requires-Dist: pre-commit>=3.5.0; extra == 'dev'
Requires-Dist: pytest-asyncio>=0.21.0; extra == 'dev'
Requires-Dist: pytest>=7.4.0; extra == 'dev'
Requires-Dist: ruff>=0.1.0; extra == 'dev'
Provides-Extra: gui
Requires-Dist: pillow>=10.0.0; extra == 'gui'
Provides-Extra: tray
Requires-Dist: pillow>=10.0.0; extra == 'tray'
Requires-Dist: pystray>=0.19.0; extra == 'tray'
Provides-Extra: vision
Requires-Dist: mlx-vlm>=0.3.9; extra == 'vision'
Requires-Dist: pillow>=10.0.0; extra == 'vision'
Requires-Dist: sentencepiece>=0.2.0; extra == 'vision'
Requires-Dist: tokenizers>=0.21.0; extra == 'vision'
Requires-Dist: transformers>=4.57.3; extra == 'vision'
